{
  "indexes": [
    {
      "collectionGroup": "classMessages",
      "queryScope": "COLLECTION",
      "fields": [
        { "fieldPath": "classId", "order": "ASCENDING" },
        { "fieldPath": "timestamp", "order": "DESCENDING" }
      ]
    },
    {
      "collectionGroup": "quizResults",
      "queryScope": "COLLECTION",
      "fields": [
        { "fieldPath": "userId", "order": "ASCENDING" },
        { "fieldPath": "timestamp", "order": "DESCENDING" }
      ]
    },
    {
      "collectionGroup": "notifications",
      "queryScope": "COLLECTION",
      "fields": [
        { "fieldPath": "userId", "order": "ASCENDING" },
        { "fieldPath": "createdAt", "order": "DESCENDING" }
      ]
    }
  ],
  "fieldOverrides": []
}
